goxlrutilityapi/__init__.py
goxlrutilityapi/__main__.py
goxlrutilityapi/_version.py
goxlrutilityapi/base.py
goxlrutilityapi/const.py
goxlrutilityapi/exceptions.py
goxlrutilityapi/logger.py
goxlrutilityapi/websocket_client.py
goxlrutilityapi/helpers/__init__.py
goxlrutilityapi/helpers/tests/__init__.py
goxlrutilityapi/helpers/tests/models/__init__.py
goxlrutilityapi/helpers/tests/models/map_item.py
goxlrutilityapi/helpers/tests/models/patch.py
goxlrutilityapi/helpers/tests/models/request.py
goxlrutilityapi/helpers/tests/models/response.py
goxlrutilityapi/helpers/tests/models/status.py
goxlrutilityapi/models/__init__.py
goxlrutilityapi/models/map_item.py
goxlrutilityapi/models/patch.py
goxlrutilityapi/models/request.py
goxlrutilityapi/models/response.py
goxlrutilityapi/models/status.py
goxlrutilityapi-1.2.5.dist-info/METADATA
goxlrutilityapi-1.2.5.dist-info/WHEEL
goxlrutilityapi-1.2.5.dist-info/top_level.txt
goxlrutilityapi-1.2.5.dist-info/RECORD
