Metadata-Version: 2.4
Name: goxlrutilityapi
Version: 1.2.5
Summary: GoXLR Utility API
Home-page: https://github.com/timmo001/goxlr-utility-api-py
Author: Aidan Timson (Timmo)
Author-email: aidan@timmo.dev
License: MIT
Keywords: GoXLR Utility API
Requires-Dist: aiohttp>=3.12.15
Requires-Dist: polyfactory>=2.0.1
Requires-Dist: typer>=0.7.0
Dynamic: author
Dynamic: author-email
Dynamic: home-page
Dynamic: keywords
Dynamic: license
Dynamic: requires-dist
Dynamic: summary
